jdl.pyd
jpy-0.9.0.jar
jpy.pyd
jpyutil.py
jpyutil.pyc
illumon_jpy-1.20180803.21.dist-info/DESCRIPTION.rst
illumon_jpy-1.20180803.21.dist-info/METADATA
illumon_jpy-1.20180803.21.dist-info/RECORD
illumon_jpy-1.20180803.21.dist-info/WHEEL
illumon_jpy-1.20180803.21.dist-info/metadata.json
illumon_jpy-1.20180803.21.dist-info/top_level.txt
