Metadata-Version: 2.0
Name: illumon-jpy
Version: 1.20180803.21
Summary: Illumon fork of jpy Bi-directional Python-Java bridge
Home-page: https://github.com/bcdev/jpy
Author: Illumon Inc.
Author-email: python@illumon.com
License: Apache 2.0
Download-URL: https://pypi.python.org/pypi/jpy/1.20180803.021
Platform: Windows
Platform: Linux
Platform: Darwin
Classifier: Development Status :: 4 - Beta
Classifier: Intended Audience :: Developers
Classifier: License :: OSI Approved :: Apache Software License
Classifier: Programming Language :: Python :: 2
Classifier: Programming Language :: Python :: 2.7
Classifier: Programming Language :: Python :: 3
Classifier: Programming Language :: Python :: 3.3
Classifier: Programming Language :: Python :: 3.4
Classifier: Programming Language :: Python :: 3.5
Requires-Dist: dill
Requires-Dist: numpy (==1.14.5)
Requires-Dist: pandas
Requires-Dist: wrapt
